.travis.yml
AUTHORS
ChangeLog
LICENSE
README.md
pylintrc
pyproject.toml
setup.cfg
setup.py
tox.ini
docs/Code-of-Conduct.md
docs/Concepts.md
docs/Contributing.md
docs/Generic_SNMP_Polling_DSL.md
docs/Installation.md
docs/System_Metrics.md
docs/device_polling_flow.svg
docs/panoptes_architecture.png
examples/conf/influxdb_consumer.ini
examples/conf/logging.ini
examples/conf/panoptes.ini
examples/plugins/discovery/localhost.json
examples/plugins/discovery/plugin_discovery_from_json_file.panoptes-plugin
examples/plugins/enrichment/plugin_enrichment_interface.panoptes-plugin
examples/plugins/polling/plugin_polling_device_interface_metrics.panoptes-plugin
tests/__init__.py
tests/helpers.py
tests/mock_kafka_consumer.py
tests/mock_panoptes_consumer.py
tests/mock_panoptes_lock.py
tests/mock_panoptes_producer.py
tests/mock_redis.py
tests/mock_requests_responses.py
tests/test_base_plugin.py
tests/test_framework.py
tests/test_framework_enrichment.py
tests/test_framework_enrichment_cache.py
tests/test_framework_metrics.py
tests/test_framework_plugins_helpers.py
tests/test_helpers.py
tests/test_key_value_store.py
tests/test_lock.py
tests/test_panoptes_consumer.py
tests/test_ping.py
tests/test_plugin_agent.py
tests/test_plugin_context.py
tests/test_plugin_manager.py
tests/test_runner.py
tests/test_scheduler.py
tests/test_schema.py
tests/test_secrets.py
tests/test_snmp_connections.py
tests/test_validators.py
tests/config_files/test_panoptes_config.ini
tests/config_files/test_panoptes_config_bad_consumer_cfg.ini
tests/config_files/test_panoptes_config_bad_consumer_cfg_1.ini
tests/config_files/test_panoptes_config_bad_consumer_cfg_2.ini
tests/config_files/test_panoptes_config_bad_discovery_path.ini
tests/config_files/test_panoptes_config_bad_discovery_path_inaccessible.ini
tests/config_files/test_panoptes_config_bad_enrichment_path.ini
tests/config_files/test_panoptes_config_bad_enrichment_path_inaccessible.ini
tests/config_files/test_panoptes_config_bad_host_null.ini
yahoo_panoptes.egg-info/PKG-INFO
yahoo_panoptes.egg-info/SOURCES.txt
yahoo_panoptes.egg-info/dependency_links.txt
yahoo_panoptes.egg-info/entry_points.txt
yahoo_panoptes.egg-info/not-zip-safe
yahoo_panoptes.egg-info/pbr.json
yahoo_panoptes.egg-info/requires.txt
yahoo_panoptes.egg-info/top_level.txt
