Metadata-Version: 2.1
Name: yahoo-panoptes
Version: 1.3.2
Summary: Network Telemetry And Monitoring
Home-page: https://getpanoptes.io
Author: Network Automation Team @ Verizon Media
Author-email: network-automation@verizonmedia.com
License: Apache 2.0
Platform: UNKNOWN
Classifier: Development Status :: 5 - Production/Stable
Classifier: Environment :: No Input/Output (Daemon)
Classifier: Intended Audience :: Other Audience
Classifier: Operating System :: POSIX :: Linux
Classifier: Programming Language :: Python :: 3
Classifier: Programming Language :: Python :: 3.6
Classifier: Programming Language :: Python
Classifier: Topic :: System :: Networking :: Monitoring
Provides-Extra: dev
Provides-Extra: doc_build
